typeschemalib/typeschemalib.py
typeschemalib-1.7.dist-info/LICENSE
typeschemalib-1.7.dist-info/METADATA
typeschemalib-1.7.dist-info/WHEEL
typeschemalib-1.7.dist-info/top_level.txt
typeschemalib-1.7.dist-info/RECORD
