Metadata-Version: 2.1
Name: typeschemalib
Version: 1.7
Summary: A yaml like schema that can be used to check dictionaries for correct schema
Home-page: https://github.com/JakeRoggenbuck/typeschemalib
Author: Jake Roggenbuck
Author-email: jake@jr0.org
License: MIT
Platform: UNKNOWN
